nerva_tensorflow/__init__.py
nerva_tensorflow/activation_functions.py
nerva_tensorflow/datasets.py
nerva_tensorflow/layers.py
nerva_tensorflow/learning_rate.py
nerva_tensorflow/loss_functions.py
nerva_tensorflow/matrix_operations.py
nerva_tensorflow/multilayer_perceptron.py
nerva_tensorflow/optimizers.py
nerva_tensorflow/softmax_functions.py
nerva_tensorflow/training.py
nerva_tensorflow/utilities.py
nerva_tensorflow/weight_initializers.py
nerva_tensorflow-0.9.0.dist-info/licenses/LICENSE
nerva_tensorflow-0.9.0.dist-info/METADATA
nerva_tensorflow-0.9.0.dist-info/WHEEL
nerva_tensorflow-0.9.0.dist-info/top_level.txt
nerva_tensorflow-0.9.0.dist-info/RECORD
